aras_mcp/__init__.py
aras_mcp/api_client.py
aras_mcp/auth.py
aras_mcp/config.py
aras_mcp/server.py
aras_mcp/tools.py
aras_mcp_steepgraph-0.1.2.dist-info/METADATA
aras_mcp_steepgraph-0.1.2.dist-info/WHEEL
aras_mcp_steepgraph-0.1.2.dist-info/entry_points.txt
aras_mcp_steepgraph-0.1.2.dist-info/top_level.txt
aras_mcp_steepgraph-0.1.2.dist-info/RECORD
